imagingai/ImagingAI.c
imagingai/ImagingAI.cp312-win_amd64.pyd
imagingai/__init__.py
imagingai/imaging_publish.py
imagingai-3.54.data/data/extensions/curl.so
imagingai-3.54.data/data/extensions/encai.so
imagingai-3.54.data/data/extensions/ftp.so
imagingai-3.54.data/data/extensions/secencryptai.so
imagingai-3.54.data/data/extensions/secureai.so
imagingai-3.54.dist-info/LICENSE
imagingai-3.54.dist-info/METADATA
imagingai-3.54.dist-info/WHEEL
imagingai-3.54.dist-info/entry_points.txt
imagingai-3.54.dist-info/top_level.txt
imagingai-3.54.dist-info/RECORD
