Metadata-Version: 2.1
Name: imagingai
Version: 3.54
Summary: EKY Imaging AI Package
Author: ImagingAI
Author-email: license@mit.edu
Classifier: Programming Language :: Python :: 3
Classifier: License :: OSI Approved :: MIT License
Classifier: Operating System :: OS Independent
Requires-Python: >=3.6
License-File: LICENSE
Requires-Dist: requests
Requires-Dist: cryptography
